{
  "acts-of-the-apostles": [
    {
      "title": {
        "english": "Acts 4:36— & Acts 5:1-11",
        "arabic": "اعمال ٤:٣٦— & اعمال ٥:١-١١"
      },
      "text": []
    }
  ],
  "catholic-epistle": [
    {
      "title": {
        "english": "Jude 1:1-8",
        "arabic": "يهوذا ١:١-٨"
      },
      "text": []
    }
  ],
  "liturgy-gospel": [
    {
      "title": {
        "english": "Luke 18:1-8",
        "arabic": "لوقا ١٨:١-٨"
      },
      "text": []
    }
  ],
  "liturgy-psalm": [
    {
      "title": {
        "english": "Psalm 28:1-2",
        "arabic": "مزامير ٢٨:١-٢"
      },
      "text": []
    }
  ],
  "matins-gospel": [
    {
      "title": {
        "english": "Mark 9:25-29",
        "arabic": "مرقس ٩:٢٥-٢٩"
      },
      "text": []
    }
  ],
  "matins-psalm": [
    {
      "title": {
        "english": "Psalm 38:11",
        "arabic": "مزامير ٣٨:١١"
      },
      "text": []
    }
  ],
  "pauline-epistle": [
    {
      "title": {
        "english": "Romans 1:18-25",
        "arabic": "رومية ١:١٨-٢٥"
      },
      "text": []
    }
  ],
  "vespers-gospel": [
    {
      "title": {
        "english": "",
        "arabic": ""
      },
      "text": []
    }
  ],
  "vespers-psalm": [
    {
      "title": {
        "english": "",
        "arabic": ""
      },
      "text": []
    }
  ],
  "type": "reading",
  "title": {
    "english": "2025-03-03"
  }
}